LICENSE.txt
README.md
setup.py
kadita/DeepFace.py
kadita/FingerPrint.py
kadita/__init__.py
kadita.egg-info/PKG-INFO
kadita.egg-info/SOURCES.txt
kadita.egg-info/dependency_links.txt
kadita.egg-info/entry_points.txt
kadita.egg-info/top_level.txt
kadita/basemodels/ArcFace.py
kadita/basemodels/DeepID.py
kadita/basemodels/DlibResNet.py
kadita/basemodels/DlibWrapper.py
kadita/basemodels/Facenet.py
kadita/basemodels/Facenet512.py
kadita/basemodels/FbDeepFace.py
kadita/basemodels/OpenFace.py
kadita/basemodels/SFace.py
kadita/basemodels/VGGFace.py
kadita/basemodels/__init__.py
kadita/commons/__init__.py
kadita/commons/distance.py
kadita/commons/functions.py
kadita/commons/realtime.py
kadita/detectors/DlibWrapper.py
kadita/detectors/FaceDetector.py
kadita/detectors/MediapipeWrapper.py
kadita/detectors/MtcnnWrapper.py
kadita/detectors/OpenCvWrapper.py
kadita/detectors/RetinaFaceWrapper.py
kadita/detectors/SsdWrapper.py
kadita/detectors/YoloWrapper.py
kadita/detectors/YunetWrapper.py
kadita/detectors/__init__.py
kadita/extendedmodels/Age.py
kadita/extendedmodels/Emotion.py
kadita/extendedmodels/Gender.py
kadita/extendedmodels/Race.py
kadita/extendedmodels/__init__.py
kadita/fingerprintmatcher/__init__.py
kadita/fingerprintmatcher/fingerprint_matcher.py
kadita/models/__init__.py
kadita/vision/EyeAR.py
kadita/vision/MouthAR.py
kadita/vision/__init__.py
kadita/vision/trackobject.py
kadita/yaml/__init__.py
kadita/yaml/data.py
kadita/yaml/timer.py
kadita/yolo/__init__.py
kadita/yolo/image.py
kadita/yolo/routine.py