Metadata-Version: 2.1
Name: kadita
Version: 0.0.14
Summary: Kadita Computer Vision
Home-page: https://github.com/Kastara-Digital-Technology/KaditaCV
Author: Firza Ichlasul Amal Ariansyah
Author-email: napija25@gmail.com
Classifier: Programming Language :: Python :: 3
Classifier: License :: OSI Approved :: MIT License
Classifier: Operating System :: OS Independent
Requires-Python: >=3.5.5
License-File: LICENSE.txt
